__init__.py
hp816x.py
hp816x-0.0.2.dist-info/LICENSE
hp816x-0.0.2.dist-info/METADATA
hp816x-0.0.2.dist-info/WHEEL
hp816x-0.0.2.dist-info/top_level.txt
hp816x-0.0.2.dist-info/RECORD
