Metadata-Version: 2.1
Name: hp816x
Version: 0.0.2
Summary: A Python wrapper for the HP816x DLL library
Author-email: Yifei Liu <liuyifei0905@gmail.com>
License: Copyright (c) 2022 Yifei Liu        
Project-URL: Homepage, https://github.com/EzekielDaun/hp816x-py
Project-URL: Bug Tracker, https://github.com/EzekielDaun/hp816x-py/issues
Classifier: Programming Language :: Python :: 3
Classifier: License :: OSI Approved :: MIT License
Classifier: Operating System :: Microsoft :: Windows
Requires-Python: >=3.4
License-File: LICENSE
